ashishbansal_101703113_topsis/__init__.py
ashishbansal_101703113_topsis/topsis.py
ashishbansal_101703113_topsis-0.0.1.dist-info/LICENSE.txt
ashishbansal_101703113_topsis-0.0.1.dist-info/METADATA
ashishbansal_101703113_topsis-0.0.1.dist-info/WHEEL
ashishbansal_101703113_topsis-0.0.1.dist-info/top_level.txt
ashishbansal_101703113_topsis-0.0.1.dist-info/RECORD
